pytest_embedded_nuttx/__init__.py
pytest_embedded_nuttx/app.py
pytest_embedded_nuttx/dut.py
pytest_embedded_nuttx/qemu.py
pytest_embedded_nuttx/serial.py
pytest_embedded_nuttx-2.6.0.dist-info/licenses/LICENSE
pytest_embedded_nuttx-2.6.0.dist-info/WHEEL
pytest_embedded_nuttx-2.6.0.dist-info/METADATA
pytest_embedded_nuttx-2.6.0.dist-info/RECORD
